gevent_fastcgi
tests
