Metadata-Version: 1.1
Name: gevent-fastcgi
Version: 1.1.0.0
Summary: FastCGI/WSGI client and server implemented using gevent
Home-page: http://github.com/momyc/gevent-fastcgi
Author: Alexander Kulakov
Author-email: a.kulakov@mail.ru
License: MIT
Keywords: fastcgi gevent wsgi
Platform: UNKNOWN
Classifier: Development Status :: 5 - Production/Stable
Classifier: License :: OSI Approved :: MIT License
Classifier: Programming Language :: Python :: 2
Classifier: Programming Language :: Python :: 2.6
Classifier: Programming Language :: Python :: 2.7
Classifier: Programming Language :: Python :: 3
Classifier: Programming Language :: Python :: 3.5
Classifier: Programming Language :: Python :: 3.6
Classifier: Topic :: Internet :: WWW/HTTP :: WSGI :: Server
